hw_event_ingress/__init__.py
hw_event_ingress/rabbit.py
hw_event_ingress/registry.py
hw_event_ingress-0.3.0.dist-info/WHEEL
hw_event_ingress-0.3.0.dist-info/METADATA
hw_event_ingress-0.3.0.dist-info/RECORD
